Metadata-Version: 2.1
Name: self-projection
Version: 0.2.2
Summary: SelfProjection is a PyTorch-based neural network layer designed to transform and project high-dimensional data.
Home-page: https://github.com/Sombressoul/self-projection
Author: Konstantin Bashinskiy
Author-email: sombressoul@gmail.com
License: Apache
Keywords: machine learning,deep learning,pytorch layers,pytorch modules
Classifier: Intended Audience :: Science/Research
Classifier: Development Status :: 4 - Beta
Classifier: License :: OSI Approved :: Apache Software License
Classifier: Programming Language :: Python :: 3.10
Classifier: Programming Language :: Python :: 3.11
Classifier: Topic :: Scientific/Engineering :: Artificial Intelligence
Requires-Python: >=3.10.0
License-File: LICENSE
Requires-Dist: torch >=2.0.0
